cocotb_job/__init__.py
cocotb_job/client.py
cocotb_job/executor.py
cocotb_job/vcd_utils.py
cocotb_job/wave_api.py
cocotb_job-0.0.12.dist-info/LICENSE
cocotb_job-0.0.12.dist-info/METADATA
cocotb_job-0.0.12.dist-info/WHEEL
cocotb_job-0.0.12.dist-info/top_level.txt
cocotb_job-0.0.12.dist-info/RECORD
